{
  "retention": {
    "historyDays": 7,
    "maxExecutionsPerJob": 10
  },
  "notifications": {
    "batchWindowSeconds": 3,
    "toastDurationSeconds": 6,
    "groupByTool": true
  },
  "jobs": [
    {
      "id": "job_1776585953740",
      "name": "Deploy Demo Artifact",
      "tool": "deployArtifact",
      "parameters": {
        "artifactId": "demo"
      },
      "schedule": {
        "frequency": "once",
        "days": [],
        "time": "08:06",
        "timezone": "UTC",
        "cron": "6 8 * * *"
      },
      "retry": {
        "enabled": false,
        "maxRetries": 2,
        "delayMinutes": 5,
        "timeoutSeconds": 30
      },
      "enabled": false,
      "createdAt": "2026-04-19T08:05:53.740Z",
      "lastRun": "2026-04-19T08:06:05.032Z",
      "nextRun": null,
      "lastStatus": "SUCCESS"
    },
    {
      "id": "job_1776597159364",
      "name": "deploy demo 2",
      "tool": "deployArtifact",
      "parameters": {
        "artifactId": "demo"
      },
      "schedule": {
        "frequency": "once",
        "days": [],
        "time": "11:15",
        "cron": "15 11 * * *",
        "timezone": "UTC"
      },
      "retry": {
        "enabled": true,
        "maxRetries": 2,
        "delayMinutes": 5,
        "timeoutSeconds": 30
      },
      "enabled": false,
      "createdAt": "2026-04-19T11:12:39.364Z",
      "lastRun": "2026-04-19T11:15:07.201Z",
      "nextRun": null,
      "lastStatus": "SUCCESS"
    }
  ]
}